wapiti/urls.py
wapiti/helpers.py
wapiti/admin.py
wapiti/parsers.py
wapiti/modelapi.py
wapiti/conf.py
wapiti/models.py
wapiti/__init__.py
wapiti/exceptions.py
wapiti/settings.py
wapiti/migrations/0001_initial.py
wapiti/migrations/__init__.py
wapiti/tests/test_parsers.py
wapiti/tests/__init__.py
wapiti/views/interface.py
wapiti/views/__init__.py
wapiti/views/base_view.py
wapiti/views/object_views.py
wapiti/south_migrations/0003_auto__del_field_limittracking_session__add_field_limittracking_session.py
wapiti/south_migrations/0005_auto__add_logitem.py
wapiti/south_migrations/0004_auto__add_field_limittracking_ip.py
wapiti/south_migrations/0001_initial.py
wapiti/south_migrations/0002_auto__add_limittracking__add_limit.py
wapiti/south_migrations/__init__.py
django_wapiti-0.0.3.dist-info/METADATA
django_wapiti-0.0.3.dist-info/DESCRIPTION.rst
django_wapiti-0.0.3.dist-info/WHEEL
django_wapiti-0.0.3.dist-info/metadata.json
django_wapiti-0.0.3.dist-info/top_level.txt
django_wapiti-0.0.3.dist-info/RECORD
