Metadata-Version: 2.0
Name: django-wapiti
Version: 0.0.3
Summary: Django API layer
Home-page: http://github.com/ecometrica/django-wapiti/
Author: Éric St-Jean
Author-email: esj@wwd.ca
License: UNKNOWN
Keywords: django,api
Platform: UNKNOWN
Classifier: Programming Language :: Python
Classifier: Programming Language :: Python :: 2.7
Classifier: Development Status :: 3 - Alpha
Classifier: License :: OSI Approved :: BSD License
Classifier: Operating System :: POSIX
Classifier: Topic :: Software Development :: Internationalization
Classifier: Framework :: Django
